Metadata-Version: 2.1
Name: scenebox
Version: 0.2.81
Summary: Caliber Data Labs Clients package
Author: Caliber Data labs
Author-email: yaser@caliberdatalabs.ai
Classifier: Programming Language :: Python :: 3
Classifier: License :: OSI Approved :: MIT License
Classifier: Operating System :: OS Independent
Requires-Python: >=3.6
Requires-Dist: wheel (==0.36.2)
Requires-Dist: diskcache (==4.1.0)
Requires-Dist: deprecated (==1.2.7)
Requires-Dist: pytz (==2019.2)
Requires-Dist: python-dateutil (==2.8.1)
Requires-Dist: requests (==2.23.0)
Requires-Dist: ffmpeg-python (==0.2.0)
Requires-Dist: Pillow (==10.0.0)
Requires-Dist: tqdm (==4.61.2)
Requires-Dist: packaging (==21.3)
Requires-Dist: numpy (>=1.17.0)
Requires-Dist: webdataset (==0.2.26)
